[{"category":"Performance Calendar time of year","headline":"27. The real challenge: making the entire web fast","urls":["http://calendar.perfplanet.com/2013/making-the-entire-web-fast/"]},{"category":"Performance Calendar time of year","headline":"28. React's diff algorithm","urls":["http://calendar.perfplanet.com/2013/diff/"]},{"category":"Performance Calendar time of year","headline":"29. Selling Web Performance to the Business","urls":["http://calendar.perfplanet.com/2013/selling-to-the-business/"]},{"category":"Performance Calendar time of year","headline":"30. Automatically Detecting 3PC with ThirdPartyContent.org","urls":["http://calendar.perfplanet.com/2013/thirdpartycontent/"]},{"category":"Performance Calendar time of year","headline":"31. JavaScript Performance Analysis: Keeping the Big Picture","urls":["http://calendar.perfplanet.com/2013/javascript-performance-big-picture/"]},{"category":"Performance Calendar time of year","headline":"Can Do vs Can't Do culture","urls":["http://recode.net/2014/01/01/can-do-vs-cant-do-culture/"]},{"category":"Performance Calendar time of year","headline":"Zappos is going holacritic: no titles, no managers, no hierarchy","urls":["http://qz.com/161210/zappos-is-going-holacratic-no-job-titles-no-managers-no-hierarchy/"]},{"category":"Commerce","headline":"PayPal steps up small business lending","urls":["http://www.mercurynews.com/business/ci_24835552/paypal-steps-up-small-business-lending"]},{"category":"Commerce","headline":"Epic One-time smart credit card","urls":["http://www.forbes.com/sites/adamtanner/2014/01/03/heres-how-credit-cards-can-thwart-target-style-hacking/"]},{"category":"The Rest of the Crop","headline":"4 keys to 100% uptime with node.js","urls":["http://engineering.spanishdict.com/blog/2013/12/20/the-4-keys-to-100-uptime-with-nodejs"]},{"category":"The Rest of the Crop","headline":"Working on related  node.js modules locally","urls":["http://www.asyncdev.net/2013/12/working-on-related-node-modules-locally/"]},{"category":"The Rest of the Crop","headline":"Mobile devices will be biggest security threat in 2014","urls":["http://mashable.com/2013/12/27/mobile-devices-security-threat/"]},{"category":"The Rest of the Crop","headline":"10 Graphic design cheat sheets","urls":["http://inspiredm.com/10-graphic-design-cheat-sheets/"]},{"category":"The Rest of the Crop","headline":"IE10 CSS Hacks","urls":["http://www.impressivewebs.com/ie10-css-hacks/"]},{"category":"The Rest of the Crop","headline":"Badass Javascript","urls":["http://badassjs.com/"]},{"category":"The Rest of the Crop","headline":"Optimal Characters per line","urls":["http://mikeyanderson.com/optimal_characters_per_line"]},{"category":"The Rest of the Crop","headline":"Tips for improving mobile forms","urls":["http://econsultancy.com/blog/63513-10-simple-tips-for-improving-mobile-form-ux"]},{"category":"The Rest of the Crop","headline":"Creating your first grunt plugin","urls":["http://javascriptplayground.com/blog/2014/01/creating-your-first-grunt-plugin/"]},{"category":"The Rest of the Crop","headline":"CSS Blend Modes coming","urls":["https://medium.com/p/6b51bf53743a"]},{"category":"The Rest of the Crop","headline":"Responsive iframes","urls":["http://responsivenews.co.uk/post/71845174511/responsive-iframes"]},{"category":"The Rest of the Crop","headline":"Tutorial: HTML5 Desktop Apps with Node-webkit","urls":["http://net.tutsplus.com/tutorials/javascript-ajax/introduction-to-html5-desktop-apps-with-node-webkit/"]},{"category":"The Rest of the Crop","headline":"10 Commandments of egoless programming","urls":["http://www.codinghorror.com/blog/2006/05/the-ten-commandments-of-egoless-programming.html"]},{"category":"The Rest of the Crop","headline":"10 Must-have extensions for Chrome Developers","urls":["http://mashable.com/2013/02/19/chrome-extensions-developers/"]},{"category":"The Rest of the Crop","headline":"Managing the asynch nature of node.js","urls":["http://net.tutsplus.com/tutorials/javascript-ajax/managing-the-asynchronous-nature-of-node-js/"]},{"category":"The Rest of the Crop","headline":"JavaScript Patterns Collection","urls":["http://shichuan.github.io/javascript-patterns/"]},{"category":"The Rest of the Crop","headline":"Foundation Icon Fonts","urls":["http://zurb.com/playground/foundation-icons"]},{"category":"The Rest of the Crop","headline":"Make the world go round - Cool interactive 3-D globes","urls":["http://planetaryjs.com/"]},{"category":"The Rest of the Crop","headline":"Web platform: 5 Technologies to look forward to in 2014","urls":["http://www.smashingmagazine.com/2013/12/27/open-sourcing-projects-guide-getting-started/"]},{"category":"The Rest of the Crop","headline":"45 JS Tips, Tricks and Best Practices","urls":["http://flippinawesome.org/2013/12/23/45-useful-javascript-tips-tricks-and-best-practices/"]},{"category":"The Rest of the Crop","headline":"Tweeting Happy New Year around the world","urls":["http://twitter.github.io/interactive/newyear2014/?utm_source=dlvr.it&utm_medium=twitter"]}]